datamanager/__init__.py
datamanager/datamanager.py
datamanager/manager.py
dre_datamanager-0.1.0.dist-info/METADATA
dre_datamanager-0.1.0.dist-info/WHEEL
dre_datamanager-0.1.0.dist-info/top_level.txt
dre_datamanager-0.1.0.dist-info/RECORD
